nuvole/__init__.py
nuvole/logger.py
nuvole/server.py
nuvole/service.py
nuvole-1.0.0.dist-info/LICENSE
nuvole-1.0.0.dist-info/METADATA
nuvole-1.0.0.dist-info/WHEEL
nuvole-1.0.0.dist-info/top_level.txt
nuvole-1.0.0.dist-info/RECORD
