Metadata-Version: 2.1
Name: nuvole
Version: 1.0.0
Summary: Simple wrapper of Python tornado web framework
Home-page: https://github.com/crogeo/nuvole
Author: crogeo.org
Author-email: c.crogeo@gmail.com
License: MIT License
License-File: LICENSE
Requires-Dist: tornado
